melodia/__init__.py
melodia/core/__init__.py
melodia/core/note.py
melodia/core/sgnature.py
melodia/core/signature.py
melodia/core/tone.py
melodia/core/track.py
melodia/io/__init__.py
melodia/io/midi.py
melodia/music/__init__.py
melodia/music/chord.py
melodia-1.1.dist-info/LICENSE.txt
melodia-1.1.dist-info/METADATA
melodia-1.1.dist-info/WHEEL
melodia-1.1.dist-info/top_level.txt
melodia-1.1.dist-info/RECORD
